AUTHORS.rst
CONTRIBUTING.rst
HISTORY.rst
LICENSE
MANIFEST.in
README.rst
setup.cfg
setup.py
cronshield/__init__.py
cronshield/cli.py
cronshield/cronshield.py
cronshield.egg-info/PKG-INFO
cronshield.egg-info/SOURCES.txt
cronshield.egg-info/dependency_links.txt
cronshield.egg-info/entry_points.txt
cronshield.egg-info/not-zip-safe
cronshield.egg-info/requires.txt
cronshield.egg-info/top_level.txt
docs/Makefile
docs/authors.rst
docs/conf.py
docs/contributing.rst
docs/history.rst
docs/index.rst
docs/installation.rst
docs/make.bat
docs/readme.rst
docs/usage.rst
tests/__init__.py
tests/test_cronshield.py
tests/test_max_failure_interval.py